README.txt
setup.py
newsuper/__init__.py
newsuper/_newsuper.py
newsuper/test.py
newsuper.egg-info/PKG-INFO
newsuper.egg-info/SOURCES.txt
newsuper.egg-info/dependency_links.txt
newsuper.egg-info/top_level.txt