Metadata-Version: 1.0
Name: newsuper
Version: 0.3c
Summary: Python 3.x super() in 2.x
Home-page: http://pypi.python.org/pypi/newsuper/
Author: invlpg
Author-email: invlpg@gmail.com
License: MIT
Platform: UNKNOWN
